{
  "experiment": "E1_MNIST",
  "model_mode": "v4",
  "seed": 1,
  "dataset": {
    "train": 60000,
    "test": 10000,
    "input_dim": 784,
    "classes": 10
  },
  "v4_sparse": {
    "hidden": 128,
    "states": 4,
    "gate_hidden": 16,
    "use_skip": false,
    "params": 484018,
    "accuracy": 0.9282,
    "train_time_sec": 73.58376010000939,
    "inference_time_sec": 0.2715372999664396,
    "estimated_sparse_inference_flops_per_sample": 265472,
    "estimated_dense_executed_flops_per_sample": 965888,
    "history": [
      {
        "epoch": 1,
        "loss": 1.1871006737452119,
        "test_acc": 0.8499
      },
      {
        "epoch": 2,
        "loss": 0.4394882545251189,
        "test_acc": 0.8959
      },
      {
        "epoch": 3,
        "loss": 0.32448524756201697,
        "test_acc": 0.9109
      },
      {
        "epoch": 4,
        "loss": 0.2735075854166977,
        "test_acc": 0.9218
      },
      {
        "epoch": 5,
        "loss": 0.2394162648856816,
        "test_acc": 0.9282
      }
    ],
    "gate_usage_l1_by_class": [
      [
        646,
        0,
        331,
        3
      ],
      [
        8,
        0,
        1127,
        0
      ],
      [
        76,
        0,
        955,
        1
      ],
      [
        224,
        0,
        786,
        0
      ],
      [
        958,
        0,
        23,
        1
      ],
      [
        768,
        0,
        124,
        0
      ],
      [
        439,
        0,
        517,
        2
      ],
      [
        840,
        1,
        187,
        0
      ],
      [
        811,
        0,
        163,
        0
      ],
      [
        991,
        1,
        17,
        0
      ]
    ],
    "gate_usage_l2_by_class": [
      [
        8,
        196,
        776,
        0
      ],
      [
        0,
        1,
        1134,
        0
      ],
      [
        0,
        51,
        981,
        0
      ],
      [
        0,
        22,
        988,
        0
      ],
      [
        0,
        472,
        510,
        0
      ],
      [
        0,
        13,
        879,
        0
      ],
      [
        0,
        454,
        504,
        0
      ],
      [
        0,
        41,
        987,
        0
      ],
      [
        0,
        27,
        947,
        0
      ],
      [
        0,
        196,
        813,
        0
      ]
    ]
  }
}